stretch_tools/__init__.py
stretch_tools/df_tools.py
stretch_tools/es_tools.py
stretch_tools-0.1.6.dist-info/METADATA
stretch_tools-0.1.6.dist-info/WHEEL
stretch_tools-0.1.6.dist-info/top_level.txt
stretch_tools-0.1.6.dist-info/RECORD
