Metadata-Version: 2.2
Name: stretch-tools
Version: 0.1.6
Summary: Add your description here
Requires-Python: >=3.12
Requires-Dist: elasticsearch>=8.17.1
Requires-Dist: elasticsearch-dsl>=8.17.1
Requires-Dist: pandas>=2.2.3
